callooktools/__info__.py
callooktools/__init__.py
callooktools/__main__.py
callooktools/callookasync.py
callooktools/callooksync.py
callooktools/callooktools.py
callooktools/py.typed
callooktools-1.1.0.dist-info/LICENSE
callooktools-1.1.0.dist-info/METADATA
callooktools-1.1.0.dist-info/WHEEL
callooktools-1.1.0.dist-info/top_level.txt
callooktools-1.1.0.dist-info/RECORD
