Metadata-Version: 2.1
Name: callooktools
Version: 1.1.0
Summary: DEPRECATED - callook.info API interface in Python
Home-page: https://callooktools.miaow.io
Author: classabbyamp, 0x5c
Author-email: dev@kb6.ee, dev@0x5c.io
License: BSD 3-Clause
Platform: UNKNOWN
Classifier: License :: OSI Approved :: BSD License
Classifier: Programming Language :: Python :: 3
Classifier: Programming Language :: Python :: 3.8
Classifier: Programming Language :: Python :: 3.9
Classifier: Development Status :: 7 - Inactive
Classifier: Environment :: Console
Classifier: Intended Audience :: Developers
Classifier: Operating System :: OS Independent
Classifier: Topic :: Communications :: Ham Radio
Classifier: Framework :: AsyncIO
License-File: LICENSE
Requires-Dist: gridtools
Requires-Dist: requests ; extra != "async"
Provides-Extra: all
Requires-Dist: aiohttp ; extra == 'all'
Provides-Extra: async
Requires-Dist: aiohttp ; extra == 'async'
Provides-Extra: cli
Requires-Dist: rich ; extra == 'cli'
